flaskr/__init__.py
flaskr/auth.py
flaskr/blog.py
flaskr/db.py
flaskr/schema.sql
flaskr/static/style.css
flaskr/templates/base.html
flaskr/templates/auth/login.html
flaskr/templates/auth/register.html
flaskr/templates/blog/create.html
flaskr/templates/blog/index.html
flaskr/templates/blog/update.html
orc-flaskr/__init__.py
orc-flaskr/auth.py
orc-flaskr/blog.py
orc-flaskr/db.py
or_flaskr-1.0.0.dist-info/METADATA
or_flaskr-1.0.0.dist-info/WHEEL
or_flaskr-1.0.0.dist-info/top_level.txt
or_flaskr-1.0.0.dist-info/RECORD
