Metadata-Version: 2.1
Name: or-flaskr
Version: 1.0.0
Summary: Flask tutorial
Home-page: UNKNOWN
Author: Olivier Renault
Author-email: olivier@renaultconsulting.fr
License: UNKNOWN
Platform: UNKNOWN
Requires-Dist: flask
